{
  "pins": {
    "name": "jane",
    "title": "IO pin setup for 'jane' application on 'carol' hardware",
    "inputs": {
	  "DIP_SWITCH_3": {"addr": 34, "pull-up": 1},
	  "DIP_SWITCH_4": {"addr": 35},
	  "TOUCH_SENSOR": {"addr": 4, "touch": 1}
    },
    "outputs": {
	  "LED_BUILTIN": {"addr": 2}
    },
    "analog_inputs": {
	  "POTENTIOMETER": {"addr": 25, "speed": 3, "delay": 11, "max": 4095}
    },
    "pwm": {
	  "SERVO": {"bank": 0, "addr": 32, "frequency": 50, "resolution": 12, "init": 2048, "max": 4095},
	  "DIMMER_LED": {"bank": 1, "addr": 33, "frequency": 5000, "resolution": 12, "init": 0, "max": 4095}
    }
  }
}
